mukh/__init__.py
mukh/py.typed
mukh/core/__init__.py
mukh/core/base.py
mukh/core/model_hub.py
mukh/core/types.py
mukh/deepfake_detection/__init__.py
mukh/deepfake_detection/deepfake_detector.py
mukh/deepfake_detection/models/__init__.py
mukh/deepfake_detection/models/base.py
mukh/deepfake_detection/models/efficientnet/__init__.py
mukh/deepfake_detection/models/efficientnet/efficientnet_detector.py
mukh/deepfake_detection/models/efficientnet/architectures/__init__.py
mukh/deepfake_detection/models/efficientnet/architectures/fornet.py
mukh/deepfake_detection/models/efficientnet/architectures/tripletnet.py
mukh/deepfake_detection/models/efficientnet/architectures/weights.py
mukh/deepfake_detection/models/efficientnet/architectures/externals/__init__.py
mukh/deepfake_detection/models/efficientnet/architectures/externals/xception.py
mukh/deepfake_detection/models/efficientnet/isplutils/__init__.py
mukh/deepfake_detection/models/efficientnet/isplutils/data.py
mukh/deepfake_detection/models/efficientnet/isplutils/data_siamese.py
mukh/deepfake_detection/models/efficientnet/isplutils/split.py
mukh/deepfake_detection/models/efficientnet/isplutils/utils.py
mukh/deepfake_detection/models/resnet_inception/__init__.py
mukh/deepfake_detection/models/resnet_inception/resnet_inception_detector.py
mukh/face_detection/__init__.py
mukh/face_detection/face_detector.py
mukh/face_detection/models/__init__.py
mukh/face_detection/models/base_detector.py
mukh/face_detection/models/blazeface/__init__.py
mukh/face_detection/models/blazeface/blazeface_detector.py
mukh/face_detection/models/blazeface/blazeface_torch.py
mukh/face_detection/models/blazeface/face_extract.py
mukh/face_detection/models/blazeface/read_video.py
mukh/face_detection/models/mediapipe/__init__.py
mukh/face_detection/models/mediapipe/mediapipe_detector.py
mukh/face_detection/models/ultralight/__init__.py
mukh/face_detection/models/ultralight/ultralight_detector.py
mukh/face_detection/models/ultralight/vision/__init__.py
mukh-0.1.14.dist-info/licenses/LICENSE
mukh-0.1.14.dist-info/METADATA
mukh-0.1.14.dist-info/WHEEL
mukh-0.1.14.dist-info/top_level.txt
mukh-0.1.14.dist-info/RECORD
