Metadata-Version: 2.4
Name: mukh
Version: 0.1.14
Summary: A comprehensive face analysis library that provides unified APIs for various face-related tasks
Home-page: https://github.com/ishandutta0098/mukh
Author: Ishan Dutta
Author-email: duttaishan098@gmail.com
Project-URL: Bug Tracker, https://github.com/ishandutta0098/mukh/issues
Classifier: Programming Language :: Python :: 3
Classifier: License :: OSI Approved :: Apache Software License
Classifier: Operating System :: OS Independent
Requires-Python: >=3.10
License-File: LICENSE
Requires-Dist: matplotlib>=3.8.0
Requires-Dist: mediapipe>=0.10.0
Requires-Dist: numpy>=1.26.0
Requires-Dist: opencv-python>=4.8.0
Requires-Dist: scipy>=1.10.0
Requires-Dist: torch>=2.0.0
Requires-Dist: torchvision>=0.15.0
Requires-Dist: imageio[ffmpeg]
Requires-Dist: scikit-image
Requires-Dist: pyyaml
Requires-Dist: tqdm
Requires-Dist: face-alignment
Requires-Dist: facenet-pytorch
Requires-Dist: efficientnet_pytorch
Requires-Dist: gradio
Requires-Dist: huggingface_hub>=0.16.0
Requires-Dist: albumentations
Provides-Extra: dev
Requires-Dist: pytest>=6.0.0; extra == "dev"
Requires-Dist: pytest-cov>=2.10.0; extra == "dev"
Requires-Dist: black>=22.0.0; extra == "dev"
Requires-Dist: isort>=5.0.0; extra == "dev"
Requires-Dist: flake8>=3.8.0; extra == "dev"
Requires-Dist: mypy>=0.800; extra == "dev"
Requires-Dist: bump2version>=1.0.0; extra == "dev"
Requires-Dist: tox==3.24.3; extra == "dev"
Requires-Dist: build; extra == "dev"
Requires-Dist: twine; extra == "dev"
Requires-Dist: mkdocs-material; extra == "dev"
Requires-Dist: mkdocs-gen-files; extra == "dev"
Requires-Dist: mkdocs-literate-nav; extra == "dev"
Requires-Dist: mkdocs-section-index; extra == "dev"
Requires-Dist: mkdocstrings[python]; extra == "dev"
Requires-Dist: huggingface-hub[cli]; extra == "dev"
Dynamic: license-file
